Metadata-Version: 2.1
Name: bubbleio
Version: 0.6.1
Home-page: https://github.com/vlebert/bubbleio
Author: Valérian LEBERT
Author-email: 
License-File: LICENSE
